textxgen/__init__.py
textxgen/client.py
textxgen/config.py
textxgen/exceptions.py
textxgen/models.py
textxgen/utils.py
textxgen/endpoints/__init__.py
textxgen/endpoints/chat.py
textxgen/endpoints/completions.py
textxgen/endpoints/models.py
textxgen/tests/__init__.py
textxgen/tests/test_chat.py
textxgen/tests/test_client.py
textxgen/tests/test_completions.py
textxgen-1.0.2.dist-info/LICENSE
textxgen-1.0.2.dist-info/METADATA
textxgen-1.0.2.dist-info/WHEEL
textxgen-1.0.2.dist-info/top_level.txt
textxgen-1.0.2.dist-info/RECORD
