Metadata-Version: 2.2
Name: textxgen
Version: 1.0.2
Summary: A Python package for interacting with models
Home-page: https://github.com/Sohail-Shaikh-07/textxgen
Author: Sohail Shaikh
Author-email: support@pystack.site
Classifier: Programming Language :: Python :: 3
Classifier: License :: OSI Approved :: MIT License
Classifier: Operating System :: OS Independent
Requires-Python: >=3.8
License-File: LICENSE
Requires-Dist: requests>=2.31.0
Dynamic: author
Dynamic: author-email
Dynamic: classifier
Dynamic: description
Dynamic: description-content-type
Dynamic: home-page
Dynamic: requires-dist
Dynamic: requires-python
Dynamic: summary
